{"lat":37.3382,"lon":-121.8863,"timezone":"America/Los_Angeles","timezone_offset":-25200,"current":{"dt":1616984220,"sunrise":1616939903,"sunset":1616984779,"temp":67.5,"feels_like":55.67,"pressure":1021,"humidity":28,"dew_point":33.28,"uvi":0,"clouds":1,"visibility":10000,"wind_speed":14.97,"wind_deg":330,"weather":[{"id":800,"main":"Clear","description":"clear sky","icon":"01d"}]},"daily":[{"dt":1616961600,"sunrise":1616939903,"sunset":1616984779,"temp":{"day":77,"min":52.97,"max":78.37,"night":55.33,"eve":67.5,"morn":52.97},"feels_like":{"day":73.09,"night":51.33,"eve":61.3,"morn":49.86},"pressure":1023,"humidity":28,"dew_point":40.48,"wind_speed":3.47,"wind_deg":310,"weather":[{"id":800,"main":"Clear","description":"clear sky","icon":"01d"}],"clouds":0,"pop":0,"uvi":6.6},{"dt":1617048000,"sunrise":1617026213,"sunset":1617071232,"temp":{"day":69.35,"min":48.18,"max":71.24,"night":52.45,"eve":61.54,"morn":48.18},"feels_like":{"day":63.32,"night":48.31,"eve":56.61,"morn":44.8},"pressure":1016,"humidity":32,"dew_point":36.68,"wind_speed":6.17,"wind_deg":309,"weather":[{"id":800,"main":"Clear","description":"clear sky","icon":"01d"}],"clouds":0,"pop":0,"uvi":6.03},{"dt":1617134400,"sunrise":1617112522,"sunset":1617157685,"temp":{"day":72.41,"min":47.57,"max":75.87,"night":58.12,"eve":66.16,"morn":47.57},"feels_like":{"day":64.4,"night":53.58,"eve":61.59,"morn":41.56},"pressure":1015,"humidity":17,"dew_point":24.62,"wind_speed":6.29,"wind_deg":354,"weather":[{"id":800,"main":"Clear","description":"clear sky","icon":"01d"}],"clouds":0,"pop":0,"uvi":6.74},{"dt":1617220800,"sunrise":1617198832,"sunset":1617244138,"temp":{"day":82.02,"min":53.35,"max":82.02,"night":61.11,"eve":64.8,"morn":53.35},"feels_like":{"day":78.67,"night":57.6,"eve":62.1,"morn":48.33},"pressure":1018,"humidity":21,"dew_point":36.64,"wind_speed":1.41,"wind_deg":237,"weather":[{"id":800,"main":"Clear","description":"clear sky","icon":"01d"}],"clouds":0,"pop":0,"uvi":6.4},{"dt":1617307200,"sunrise":1617285142,"sunset":1617330591,"temp":{"day":83.91,"min":57.76,"max":83.91,"night":59.36,"eve":64.06,"morn":60.76},"feels_like":{"day":79.59,"night":55.54,"eve":60.24,"morn":56.82},"pressure":1013,"humidity":20,"dew_point":37.33,"wind_speed":3.22,"wind_deg":294,"weather":[{"id":803,"main":"Clouds","description":"broken clouds","icon":"04d"}],"clouds":68,"pop":0,"uvi":6.88},{"dt":1617393600,"sunrise":1617371453,"sunset":1617417044,"temp":{"day":80.53,"min":54.1,"max":80.53,"night":54.1,"eve":59.72,"morn":58.78},"feels_like":{"day":75.47,"night":49.93,"eve":56.39,"morn":54.93},"pressure":1014,"humidity":18,"dew_point":31.51,"wind_speed":2.93,"wind_deg":246,"weather":[{"id":800,"main":"Clear","description":"clear sky","icon":"01d"}],"clouds":1,"pop":0,"uvi":7},{"dt":1617480000,"sunrise":1617457763,"sunset":1617503497,"temp":{"day":73.22,"min":50.65,"max":73.22,"night":50.65,"eve":54.57,"morn":53.87},"feels_like":{"day":67.78,"night":48.4,"eve":52.03,"morn":49.68},"pressure":1016,"humidity":24,"dew_point":32.58,"wind_speed":3.91,"wind_deg":240,"weather":[{"id":804,"main":"Clouds","description":"overcast clouds","icon":"04d"}],"clouds":100,"pop":0,"uvi":7},{"dt":1617566400,"sunrise":1617544074,"sunset":1617589951,"temp":{"day":61.54,"min":45.84,"max":61.54,"night":45.84,"eve":51.1,"morn":50.67},"feels_like":{"day":55.53,"night":42.57,"eve":45.99,"morn":48.78},"pressure":1015,"humidity":41,"dew_point":36.05,"wind_speed":5.95,"wind_deg":305,"weather":[{"id":804,"main":"Clouds","description":"overcast clouds","icon":"04d"}],"clouds":100,"pop":0,"uvi":7}]}